README.rst
setup.py
tgext/__init__.py
tgext.chameleon_genshi.egg-info/PKG-INFO
tgext.chameleon_genshi.egg-info/SOURCES.txt
tgext.chameleon_genshi.egg-info/dependency_links.txt
tgext.chameleon_genshi.egg-info/entry_points.txt
tgext.chameleon_genshi.egg-info/namespace_packages.txt
tgext.chameleon_genshi.egg-info/not-zip-safe
tgext.chameleon_genshi.egg-info/requires.txt
tgext.chameleon_genshi.egg-info/top_level.txt
tgext/chameleon_genshi/__init__.py
tgext/chameleon_genshi/renderer.py