Metadata-Version: 1.1
Name: tgext.chameleon-genshi
Version: 0.0.1
Summary: Chameleon Genshi rendering engine for TurboGears2
Home-page: https://github.com/TurboGears/tgext.chameleon_genshi
Author: Alessandro Molina
Author-email: alessandro.molina@axant.it
License: MIT
Keywords: turbogears2.extension
Platform: UNKNOWN
Classifier: Environment :: Web Environment
Classifier: Topic :: Software Development :: Libraries :: Python Modules
Classifier: Framework :: TurboGears
